odoo/addons/l10n_ro_edi_ubl/README.rst
odoo/addons/l10n_ro_edi_ubl/__init__.py
odoo/addons/l10n_ro_edi_ubl/__manifest__.py
odoo/addons/l10n_ro_edi_ubl/data/xsd-1.1/docxchange-commons.xsd
odoo/addons/l10n_ro_edi_ubl/data/xsd-1.1/docxchange-invoice-extended.xsd
odoo/addons/l10n_ro_edi_ubl/data/xsd-2.1/UBL-Invoice-2.1.xsd
odoo/addons/l10n_ro_edi_ubl/models/__init__.py
odoo/addons/l10n_ro_edi_ubl/models/account_invoice.py
odoo/addons/l10n_ro_edi_ubl/models/res_company.py
odoo/addons/l10n_ro_edi_ubl/models/res_config_settings.py
odoo/addons/l10n_ro_edi_ubl/models/res_partner.py
odoo/addons/l10n_ro_edi_ubl/models/ubl.py
odoo/addons/l10n_ro_edi_ubl/readme/CONTRIBUTORS.rst
odoo/addons/l10n_ro_edi_ubl/readme/DESCRIPTION.rst
odoo/addons/l10n_ro_edi_ubl/static/description/icon.png
odoo/addons/l10n_ro_edi_ubl/static/description/icon.svg
odoo/addons/l10n_ro_edi_ubl/static/description/index.html
odoo/addons/l10n_ro_edi_ubl/views/account_invoice.xml
odoo/addons/l10n_ro_edi_ubl/views/bis3_templates.xml
odoo/addons/l10n_ro_edi_ubl/views/res_config_settings_views.xml
odoo/addons/l10n_ro_edi_ubl/views/res_partner_view.xml
odoo13_addon_l10n_ro_edi_ubl-13.0.0.1.0.dist-info/METADATA
odoo13_addon_l10n_ro_edi_ubl-13.0.0.1.0.dist-info/WHEEL
odoo13_addon_l10n_ro_edi_ubl-13.0.0.1.0.dist-info/top_level.txt
odoo13_addon_l10n_ro_edi_ubl-13.0.0.1.0.dist-info/RECORD
